sahara_plugin_mapr/__init__.py
sahara_plugin_mapr/i18n.py
sahara_plugin_mapr/locale/de/LC_MESSAGES/sahara_plugin_mapr.po
sahara_plugin_mapr/locale/en_GB/LC_MESSAGES/sahara_plugin_mapr.po
sahara_plugin_mapr/plugins/__init__.py
sahara_plugin_mapr/plugins/mapr/__init__.py
sahara_plugin_mapr/plugins/mapr/images.py
sahara_plugin_mapr/plugins/mapr/plugin.py
sahara_plugin_mapr/plugins/mapr/abstract/__init__.py
sahara_plugin_mapr/plugins/mapr/abstract/cluster_context.py
sahara_plugin_mapr/plugins/mapr/abstract/cluster_validator.py
sahara_plugin_mapr/plugins/mapr/abstract/configurer.py
sahara_plugin_mapr/plugins/mapr/abstract/health_checker.py
sahara_plugin_mapr/plugins/mapr/abstract/node_manager.py
sahara_plugin_mapr/plugins/mapr/abstract/version_handler.py
sahara_plugin_mapr/plugins/mapr/base/__init__.py
sahara_plugin_mapr/plugins/mapr/base/base_cluster_configurer.py
sahara_plugin_mapr/plugins/mapr/base/base_cluster_context.py
sahara_plugin_mapr/plugins/mapr/base/base_cluster_validator.py
sahara_plugin_mapr/plugins/mapr/base/base_edp_engine.py
sahara_plugin_mapr/plugins/mapr/base/base_health_checker.py
sahara_plugin_mapr/plugins/mapr/base/base_node_manager.py
sahara_plugin_mapr/plugins/mapr/base/base_version_handler.py
sahara_plugin_mapr/plugins/mapr/domain/__init__.py
sahara_plugin_mapr/plugins/mapr/domain/configuration_file.py
sahara_plugin_mapr/plugins/mapr/domain/distro.py
sahara_plugin_mapr/plugins/mapr/domain/node_process.py
sahara_plugin_mapr/plugins/mapr/domain/service.py
sahara_plugin_mapr/plugins/mapr/resources/add_mapr_repo.sh
sahara_plugin_mapr/plugins/mapr/resources/add_security_repos.sh
sahara_plugin_mapr/plugins/mapr/resources/create_disk_list_file.sh
sahara_plugin_mapr/plugins/mapr/resources/install_java.sh
sahara_plugin_mapr/plugins/mapr/resources/install_mysql.sh
sahara_plugin_mapr/plugins/mapr/resources/install_mysql_client.sh
sahara_plugin_mapr/plugins/mapr/resources/install_scala.sh
sahara_plugin_mapr/plugins/mapr/resources/topology.sh
sahara_plugin_mapr-10.0.0.dist-info/AUTHORS
sahara_plugin_mapr-10.0.0.dist-info/LICENSE
sahara_plugin_mapr-10.0.0.dist-info/METADATA
sahara_plugin_mapr-10.0.0.dist-info/WHEEL
sahara_plugin_mapr-10.0.0.dist-info/entry_points.txt
sahara_plugin_mapr-10.0.0.dist-info/pbr.json
sahara_plugin_mapr-10.0.0.dist-info/top_level.txt
sahara_plugin_mapr-10.0.0.dist-info/RECORD
